{
  "project": "./tsconfig.json",
  "defaultSeverity": "warning",
  "extends": [
    "tslint:latest",
    "tslint-config-standard",
    "tslint-react"
  ],
  "linterOptions": {
    "exclude": [ "node_modules/**/*.ts" ]
  },
  "rules": {
    "eofline": true,
    "import-name": false,
    "no-console": false,
    "trailing-comma": true,
    "member-access": [true, "no-public"],
    "ordered-imports":false,
    "member-ordering":false,
    "no-boolean-literal-compare": true,
    "object-literal-sort-keys":false,
    "jsx-no-lambda": false,
    "jsx-wrap-multiline": false,
    "jsx-boolean-value": false,
    "jsx-no-multiline-js": false,
    "no-submodule-imports": false,
    "interface-name": [true, "never-prefix"],
    "quotemark": [true, "single", "jsx-single"],
    "arrow-parens": [true, "ban-single-arg-parens"],
    "semicolon": [true, "never", "ignore-interfaces"],
    "no-implicit-dependencies": [true, ["pages", "components"]],
    "variable-name": [true, "ban-keywords", "check-format", "allow-pascal-case"],
    "typedef": [
      true,
      "parameter",
      "property-declaration",
      "member-variable-declaration"
    ]
  },
  "exclude": ["node_modules"]
}